{
  "deliverable": "review-high-complexity",
  "phase_a": {
    "verdict": "pass",
    "acceptance_criteria": [
      {
        "criterion": "scripts/run-eval.sh passes shellcheck with no errors",
        "met": true
      },
      {
        "criterion": "scripts/run-eval.sh uses atomic writes (temp+mv) for all output files",
        "met": true,
        "note": "temp dir with trap EXIT cleanup"
      },
      {
        "criterion": "scripts/run-eval.sh exit codes match spec",
        "met": true,
        "note": "usage error changed from 1 to 2"
      },
      {
        "criterion": "scripts/validate-step-artifacts.sh passes shellcheck with no errors",
        "met": true
      },
      {
        "criterion": "scripts/validate-step-artifacts.sh sources hooks/lib/validate.sh correctly",
        "met": true
      },
      {
        "criterion": "No command substitution under set -eu swallows failures silently",
        "met": true,
        "note": "for-in loops converted to while-read from temp files"
      }
    ]
  },
  "phase_b": {
    "verdict": "pass",
    "dimensions": [
      {
        "name": "correctness",
        "verdict": "pass",
        "evidence": "yq --arg converted to env(), exit codes fixed, absolute paths used"
      },
      {
        "name": "unplanned-changes",
        "verdict": "pass",
        "evidence": "only bug fixes, no refactoring beyond scope"
      }
    ]
  },
  "overall": "pass",
  "reviewer": "parallel-agents+final-reviewer",
  "timestamp": "2026-04-02T09:55:31Z"
}
